Metadata-Version: 1.0
Name: normbipy
Version: 0.1
Summary: Gaussian and Binomial distributions
Home-page: UNKNOWN
Author: ['Mohamed Nabil']
Author-email: UNKNOWN
License: UNKNOWN
Platform: UNKNOWN
